setup.py
open_widget_framework/__init__.py
open_widget_framework/apps.py
open_widget_framework/models.py
open_widget_framework/react_fields.py
open_widget_framework/settings.py
open_widget_framework/test_settings.py
open_widget_framework/urls.py
open_widget_framework/utils.py
open_widget_framework/views.py
open_widget_framework/widget_class_base.py
open_widget_framework/widget_classes.py
open_widget_framework/widget_serializer.py
open_widget_framework.egg-info/PKG-INFO
open_widget_framework.egg-info/SOURCES.txt
open_widget_framework.egg-info/dependency_links.txt
open_widget_framework.egg-info/requires.txt
open_widget_framework.egg-info/top_level.txt
open_widget_framework/migrations/0001_initial.py
open_widget_framework/migrations/0002_auto_20181001_2001.py
open_widget_framework/migrations/0003_auto_20181109_2006.py
open_widget_framework/migrations/__init__.py
open_widget_framework/tests/__init__.py
open_widget_framework/tests/test_models.py
open_widget_framework/tests/test_views.py
open_widget_framework/tests/test_widget_classes.py