Metadata-Version: 1.0
Name: open-widget-framework
Version: 0.2.13
Summary: an open django framework for widget customization and management
Home-page: https://github.com/mitodl/open-widget-framework
Author: Zagaran, Inc.
Author-email: UNKNOWN
License: MIT
Platform: UNKNOWN
